[
  {
    "data": "07/21",

    "time": "10:00~12:00 2hour"
  },
  {
    "data": "07/22",

    "time": "14:00~16:00 2hour"
  },
  {
    "data": "07/23",
    "time": "14:00~16:00 2hour"
  },
  {
    "data": "07/21",

    "time": "10:00~12:00 2hour"
  },
  {
    "data": "07/22",

    "time": "14:00~16:00 2hour"
  },
  {
    "data": "07/23",
    "time": "14:00~16:00 2hour"
  },
  {
    "data": "07/21",

    "time": "10:00~12:00 2hour"
  },
  {
    "data": "07/22",

    "time": "14:00~16:00 2hour"
  },
  {
    "data": "07/23",
    "time": "14:00~16:00 2hour"
  },
  {
    "data": "07/21",

    "time": "10:00~12:00 2hour"
  },
  {
    "data": "07/22",

    "time": "14:00~16:00 2hour"
  },
  {
    "data": "07/23",
    "time": "14:00~16:00 2hour"
  }
]
